odoo/addons/mail_message_destiny_link_template/README.rst
odoo/addons/mail_message_destiny_link_template/__init__.py
odoo/addons/mail_message_destiny_link_template/__manifest__.py
odoo/addons/mail_message_destiny_link_template/data/mail_templates_chatter.xml
odoo/addons/mail_message_destiny_link_template/i18n/es.po
odoo/addons/mail_message_destiny_link_template/i18n/it.po
odoo/addons/mail_message_destiny_link_template/i18n/mail_message_destiny_link_template.pot
odoo/addons/mail_message_destiny_link_template/readme/CONTEXT.md
odoo/addons/mail_message_destiny_link_template/readme/CONTRIBUTORS.md
odoo/addons/mail_message_destiny_link_template/readme/DESCRIPTION.md
odoo/addons/mail_message_destiny_link_template/readme/USAGE.md
odoo/addons/mail_message_destiny_link_template/static/description/icon.png
odoo/addons/mail_message_destiny_link_template/static/description/index.html
odoo_addon_mail_message_destiny_link_template-18.0.1.0.0.3.dist-info/METADATA
odoo_addon_mail_message_destiny_link_template-18.0.1.0.0.3.dist-info/WHEEL
odoo_addon_mail_message_destiny_link_template-18.0.1.0.0.3.dist-info/top_level.txt
odoo_addon_mail_message_destiny_link_template-18.0.1.0.0.3.dist-info/RECORD
